{
  "shuttle": {
    "thrustForce": 26,
    "brakeFactor": 0.93,
    "brakeDepthPenalty": 0.002,
    "yawTorque": 3.5,
    "yawLateralForce": 5.2,
    "yawMaxSpeed": 4.25,
    "yawDamping": 0.988,
    "maxThrustSpeed": 90,
    "maxGravitySpeed": 225,
    "thrustAlignMinMultiplier": 0.62,
    "thrustAlignMaxMultiplier": 1.08,
    "rcsAlignMinMultiplier": 0.9,
    "rcsAlignMaxMultiplier": 1.15,
    "speedExcessReturnRate": 0.42
  },
  "map": {
    "thrustForce": 1.45,
    "brakeFactor": 0.93,
    "brakeDepthPenalty": 0.002,
    "yawTorque": 3.6,
    "yawLateralForce": 1.35,
    "yawMaxSpeed": 3.75,
    "yawDamping": 0.992,
    "maxThrustSpeed": 5,
    "speedReturnEquilibriumSpeed": 5,
    "maxGravitySpeed": 5,
    "thrustAlignMinMultiplier": 0.72,
    "thrustAlignMaxMultiplier": 1.05,
    "rcsAlignMinMultiplier": 0.9,
    "rcsAlignMaxMultiplier": 1.12,
    "speedExcessReturnRate": 0.35
  }
}
